[
  {
    "name": "Absent-Mindedness",
    "type": "Disadvantage",
    "levels": 1,
    "baseCost": -15,
    "modifierPct": 0,
    "points": -15,
    "autoCost": false,
    "page": "",
    "notes": "Easily distracted, forgetful or mentally elsewhere. Good for scholars, mystics and inventors.",
    "source": "User library",
    "tags": ["mental", "roleplay"]
  },
  {
    "name": "Addiction",
    "type": "Disadvantage",
    "levels": 1,
    "baseCost": -5,
    "modifierPct": 0,
    "points": -5,
    "autoCost": false,
    "page": "",
    "notes": "Dependency on a substance or behavior. Cost varies by availability, legality and harm.",
    "source": "User library",
    "tags": ["mental", "physical", "variable"]
  },
  {
    "name": "Bad Sight",
    "type": "Disadvantage",
    "levels": 1,
    "baseCost": -10,
    "modifierPct": 0,
    "points": -10,
    "autoCost": false,
    "page": "",
    "notes": "Impaired vision. Specify correction, setting and severity.",
    "source": "User library",
    "tags": ["physical", "sense"]
  },
  {
    "name": "Bad Temper",
    "type": "Disadvantage",
    "levels": 1,
    "baseCost": -10,
    "modifierPct": 0,
    "points": -10,
    "autoCost": false,
    "page": "",
    "notes": "Prone to anger under pressure. Add self-control details in notes.",
    "source": "User library",
    "tags": ["mental", "self-control", "roleplay"]
  },
  {
    "name": "Bloodlust",
    "type": "Disadvantage",
    "levels": 1,
    "baseCost": -10,
    "modifierPct": 0,
    "points": -10,
    "autoCost": false,
    "page": "",
    "notes": "Inclination to finish enemies rather than show mercy. Add self-control details.",
    "source": "User library",
    "tags": ["mental", "combat", "self-control"]
  },
  {
    "name": "Bully",
    "type": "Disadvantage",
    "levels": 1,
    "baseCost": -10,
    "modifierPct": 0,
    "points": -10,
    "autoCost": false,
    "page": "",
    "notes": "Tendency to dominate, intimidate or mistreat weaker people.",
    "source": "User library",
    "tags": ["mental", "social", "self-control"]
  },
  {
    "name": "Callous",
    "type": "Disadvantage",
    "levels": 1,
    "baseCost": -5,
    "modifierPct": 0,
    "points": -5,
    "autoCost": false,
    "page": "",
    "notes": "Emotionally cold or lacking compassion. Strong roleplaying disadvantage.",
    "source": "User library",
    "tags": ["mental", "social"]
  },
  {
    "name": "Charitable",
    "type": "Disadvantage",
    "levels": 1,
    "baseCost": -15,
    "modifierPct": 0,
    "points": -15,
    "autoCost": false,
    "page": "",
    "notes": "Compelled to help those in need. Add self-control details.",
    "source": "User library",
    "tags": ["mental", "social", "self-control"]
  },
  {
    "name": "Code of Honor",
    "type": "Disadvantage",
    "levels": 1,
    "baseCost": -10,
    "modifierPct": 0,
    "points": -10,
    "autoCost": false,
    "page": "",
    "notes": "Personal or cultural honor code. Specify exact code and expected behavior.",
    "source": "User library",
    "tags": ["mental", "social", "roleplay", "variable"]
  },
  {
    "name": "Compulsive Behavior",
    "type": "Disadvantage",
    "levels": 1,
    "baseCost": -5,
    "modifierPct": 0,
    "points": -5,
    "autoCost": false,
    "page": "",
    "notes": "Repeated behavior the character struggles to resist. Cost varies by severity.",
    "source": "User library",
    "tags": ["mental", "self-control", "variable"]
  },
  {
    "name": "Cowardice",
    "type": "Disadvantage",
    "levels": 1,
    "baseCost": -10,
    "modifierPct": 0,
    "points": -10,
    "autoCost": false,
    "page": "",
    "notes": "Strong fear of danger and personal risk. Add self-control details.",
    "source": "User library",
    "tags": ["mental", "fear", "self-control"]
  },
  {
    "name": "Curious",
    "type": "Disadvantage",
    "levels": 1,
    "baseCost": -5,
    "modifierPct": 0,
    "points": -5,
    "autoCost": false,
    "page": "",
    "notes": "Driven to investigate mysteries, oddities and secrets. Add self-control details.",
    "source": "User library",
    "tags": ["mental", "roleplay", "self-control"]
  },
  {
    "name": "Delusion",
    "type": "Disadvantage",
    "levels": 1,
    "baseCost": -5,
    "modifierPct": 0,
    "points": -5,
    "autoCost": false,
    "page": "",
    "notes": "False belief that affects behavior. Cost varies by severity and consequences.",
    "source": "User library",
    "tags": ["mental", "roleplay", "variable"]
  },
  {
    "name": "Dependent",
    "type": "Disadvantage",
    "levels": 1,
    "baseCost": -5,
    "modifierPct": 0,
    "points": -5,
    "autoCost": false,
    "page": "",
    "notes": "NPC who relies on the character. Cost varies by frequency and vulnerability.",
    "source": "User library",
    "tags": ["social", "npc", "variable"]
  },
  {
    "name": "Duty",
    "type": "Disadvantage",
    "levels": 1,
    "baseCost": -5,
    "modifierPct": 0,
    "points": -5,
    "autoCost": false,
    "page": "",
    "notes": "Obligation to an organization, lord, patron or cause. Cost varies by frequency and danger.",
    "source": "User library",
    "tags": ["social", "organization", "variable"]
  },
  {
    "name": "Enemy",
    "type": "Disadvantage",
    "levels": 1,
    "baseCost": -10,
    "modifierPct": 0,
    "points": -10,
    "autoCost": false,
    "page": "",
    "notes": "NPC, group or organization actively opposed to the character. Cost varies by power and appearance.",
    "source": "User library",
    "tags": ["social", "npc", "plot", "variable"]
  },
  {
    "name": "Fanaticism",
    "type": "Disadvantage",
    "levels": 1,
    "baseCost": -15,
    "modifierPct": 0,
    "points": -15,
    "autoCost": false,
    "page": "",
    "notes": "Extreme loyalty to a cause, belief, nation or group.",
    "source": "User library",
    "tags": ["mental", "ideology", "roleplay"]
  },
  {
    "name": "Gluttony",
    "type": "Disadvantage",
    "levels": 1,
    "baseCost": -5,
    "modifierPct": 0,
    "points": -5,
    "autoCost": false,
    "page": "",
    "notes": "Difficulty resisting food, drink or indulgence. Add self-control details.",
    "source": "User library",
    "tags": ["mental", "self-control"]
  },
  {
    "name": "Greed",
    "type": "Disadvantage",
    "levels": 1,
    "baseCost": -15,
    "modifierPct": 0,
    "points": -15,
    "autoCost": false,
    "page": "",
    "notes": "Strong temptation toward money, treasure or material gain. Add self-control details.",
    "source": "User library",
    "tags": ["mental", "social", "self-control"]
  },
  {
    "name": "Guilt Complex",
    "type": "Disadvantage",
    "levels": 1,
    "baseCost": -5,
    "modifierPct": 0,
    "points": -5,
    "autoCost": false,
    "page": "",
    "notes": "Prone to guilt and self-blame.",
    "source": "User library",
    "tags": ["mental", "roleplay"]
  },
  {
    "name": "Hard of Hearing",
    "type": "Disadvantage",
    "levels": 1,
    "baseCost": -10,
    "modifierPct": 0,
    "points": -10,
    "autoCost": false,
    "page": "",
    "notes": "Impaired hearing. Specify severity and correction if any.",
    "source": "User library",
    "tags": ["physical", "sense"]
  },
  {
    "name": "Honesty",
    "type": "Disadvantage",
    "levels": 1,
    "baseCost": -10,
    "modifierPct": 0,
    "points": -10,
    "autoCost": false,
    "page": "",
    "notes": "Strong respect for law and lawful behavior. Add self-control details.",
    "source": "User library",
    "tags": ["mental", "social", "self-control"]
  },
  {
    "name": "Impulsiveness",
    "type": "Disadvantage",
    "levels": 1,
    "baseCost": -10,
    "modifierPct": 0,
    "points": -10,
    "autoCost": false,
    "page": "",
    "notes": "Acts before thinking. Useful for adventurous or reckless characters.",
    "source": "User library",
    "tags": ["mental", "self-control"]
  },
  {
    "name": "Intolerance",
    "type": "Disadvantage",
    "levels": 1,
    "baseCost": -5,
    "modifierPct": 0,
    "points": -5,
    "autoCost": false,
    "page": "",
    "notes": "Prejudice against a group. Cost varies by scope and setting relevance.",
    "source": "User library",
    "tags": ["mental", "social", "variable"]
  },
  {
    "name": "Jealousy",
    "type": "Disadvantage",
    "levels": 1,
    "baseCost": -10,
    "modifierPct": 0,
    "points": -10,
    "autoCost": false,
    "page": "",
    "notes": "Resentment of rivals, attention or status given to others.",
    "source": "User library",
    "tags": ["mental", "social"]
  },
  {
    "name": "Lame",
    "type": "Disadvantage",
    "levels": 1,
    "baseCost": -10,
    "modifierPct": 0,
    "points": -10,
    "autoCost": false,
    "page": "",
    "notes": "Impaired legs or movement. Cost varies by severity.",
    "source": "User library",
    "tags": ["physical", "movement", "variable"]
  },
  {
    "name": "Lecherousness",
    "type": "Disadvantage",
    "levels": 1,
    "baseCost": -15,
    "modifierPct": 0,
    "points": -15,
    "autoCost": false,
    "page": "",
    "notes": "Prone to romantic or sexual distraction. Add self-control details.",
    "source": "User library",
    "tags": ["mental", "social", "self-control"]
  },
  {
    "name": "Low Pain Threshold",
    "type": "Disadvantage",
    "levels": 1,
    "baseCost": -10,
    "modifierPct": 0,
    "points": -10,
    "autoCost": false,
    "page": "",
    "notes": "Poor ability to function through pain.",
    "source": "User library",
    "tags": ["physical", "combat"]
  },
  {
    "name": "Miserliness",
    "type": "Disadvantage",
    "levels": 1,
    "baseCost": -10,
    "modifierPct": 0,
    "points": -10,
    "autoCost": false,
    "page": "",
    "notes": "Strong reluctance to spend money or resources. Add self-control details.",
    "source": "User library",
    "tags": ["mental", "social", "self-control"]
  },
  {
    "name": "Obsession",
    "type": "Disadvantage",
    "levels": 1,
    "baseCost": -5,
    "modifierPct": 0,
    "points": -5,
    "autoCost": false,
    "page": "",
    "notes": "Dominating goal or fixation. Cost varies by danger and scope.",
    "source": "User library",
    "tags": ["mental", "plot", "variable"]
  },
  {
    "name": "Odious Personal Habit",
    "type": "Disadvantage",
    "levels": 1,
    "baseCost": -5,
    "modifierPct": 0,
    "points": -5,
    "autoCost": true,
    "page": "",
    "notes": "Annoying, disturbing or offensive behavior. Increase levels for stronger reaction penalty.",
    "source": "User library",
    "tags": ["social", "reaction"]
  },
  {
    "name": "One Arm",
    "type": "Disadvantage",
    "levels": 1,
    "baseCost": -20,
    "modifierPct": 0,
    "points": -20,
    "autoCost": false,
    "page": "",
    "notes": "Missing or unusable arm. Specify prosthetics or compensating gear.",
    "source": "User library",
    "tags": ["physical"]
  },
  {
    "name": "One Eye",
    "type": "Disadvantage",
    "levels": 1,
    "baseCost": -15,
    "modifierPct": 0,
    "points": -15,
    "autoCost": false,
    "page": "",
    "notes": "Missing or unusable eye. Relevant to vision and depth perception.",
    "source": "User library",
    "tags": ["physical", "sense"]
  },
  {
    "name": "Overconfidence",
    "type": "Disadvantage",
    "levels": 1,
    "baseCost": -5,
    "modifierPct": 0,
    "points": -5,
    "autoCost": false,
    "page": "",
    "notes": "Believes in own ability beyond what is reasonable. Add self-control details.",
    "source": "User library",
    "tags": ["mental", "self-control", "roleplay"]
  },
  {
    "name": "Pacifism",
    "type": "Disadvantage",
    "levels": 1,
    "baseCost": -5,
    "modifierPct": 0,
    "points": -5,
    "autoCost": false,
    "page": "",
    "notes": "Moral or psychological opposition to violence. Cost varies by severity.",
    "source": "User library",
    "tags": ["mental", "combat", "variable"]
  },
  {
    "name": "Phobia",
    "type": "Disadvantage",
    "levels": 1,
    "baseCost": -5,
    "modifierPct": 0,
    "points": -5,
    "autoCost": false,
    "page": "",
    "notes": "Fear of a specific thing or situation. Cost varies by rarity and severity.",
    "source": "User library",
    "tags": ["mental", "fear", "variable"]
  },
  {
    "name": "Sense of Duty",
    "type": "Disadvantage",
    "levels": 1,
    "baseCost": -5,
    "modifierPct": 0,
    "points": -5,
    "autoCost": false,
    "page": "",
    "notes": "Strong obligation toward a person, group or cause. Cost varies by scope.",
    "source": "User library",
    "tags": ["mental", "social", "variable"]
  },
  {
    "name": "Stubbornness",
    "type": "Disadvantage",
    "levels": 1,
    "baseCost": -5,
    "modifierPct": 0,
    "points": -5,
    "autoCost": false,
    "page": "",
    "notes": "Reluctance to change opinion or back down.",
    "source": "User library",
    "tags": ["mental", "roleplay"]
  },
  {
    "name": "Truthfulness",
    "type": "Disadvantage",
    "levels": 1,
    "baseCost": -5,
    "modifierPct": 0,
    "points": -5,
    "autoCost": false,
    "page": "",
    "notes": "Difficulty lying or deceiving. Add self-control details.",
    "source": "User library",
    "tags": ["mental", "social", "self-control"]
  },
  {
    "name": "Vow",
    "type": "Disadvantage",
    "levels": 1,
    "baseCost": -5,
    "modifierPct": 0,
    "points": -5,
    "autoCost": false,
    "page": "",
    "notes": "Personal vow or oath. Cost varies by restrictiveness.",
    "source": "User library",
    "tags": ["mental", "social", "variable"]
  },
  {
    "name": "Weirdness Magnet",
    "type": "Disadvantage",
    "levels": 1,
    "baseCost": -15,
    "modifierPct": 0,
    "points": -15,
    "autoCost": false,
    "page": "",
    "notes": "Strange events tend to happen around the character.",
    "source": "User library",
    "tags": ["supernatural", "plot"]
  },
  {
    "name": "Xenophilia",
    "type": "Disadvantage",
    "levels": 1,
    "baseCost": -10,
    "modifierPct": 0,
    "points": -10,
    "autoCost": false,
    "page": "",
    "notes": "Fascination with strangers, outsiders or alien cultures. Add self-control details.",
    "source": "User library",
    "tags": ["mental", "social", "self-control"]
  }
]
